regendoc/__init__.py
regendoc/_cli.py
regendoc/actions.py
regendoc/parse.py
regendoc/py.typed
regendoc/substitute.py
regendoc-0.9.0.dist-info/LICENSE
regendoc-0.9.0.dist-info/METADATA
regendoc-0.9.0.dist-info/WHEEL
regendoc-0.9.0.dist-info/entry_points.txt
regendoc-0.9.0.dist-info/top_level.txt
regendoc-0.9.0.dist-info/RECORD
