Metadata-Version: 2.1
Name: regendoc
Version: 0.9.0
Summary: a tool to check/update simple file/shell examples in documentation
Home-page: http://github.com/pytest-dev/regendoc/
Author: Ronny Pfannschmidt
Author-email: opensource@ronnypfannschmidt.de
License: MPL2
Platform: UNKNOWN
License-File: LICENSE
Requires-Dist: typer
Requires-Dist: rich
